{
  "slug": "beginner-start",
  "title": "新手入门：从零开始的三角洲之旅",
  "description": "第一次进入三角洲行动？这篇指南将帮助你快速上手游戏基础操作和核心机制。",
  "category": "beginner",
  "author": "攻略组",
  "publishedAt": "2024-05-01",
  "updatedAt": "2024-05-15",
  "readTime": "8分钟",
  "tags": ["新手", "入门", "基础", "教程"],
  "content": "# 新手入门：从零开始的三角洲之旅\n\n欢迎来到三角洲行动！作为一款战术射击游戏，掌握基础操作和核心机制是成功的关键。\n\n## 基础操作\n\n### 移动与射击\n- **WASD**：移动\n- **Shift**：冲刺\n- **空格**：跳跃/翻越\n- **Ctrl**：蹲下\n- **Z**：趴下\n- **鼠标左键**：射击\n- **鼠标右键**：瞄准\n- **R**：换弹\n\n### 战术操作\n- **F**：互动（开门、拾取等）\n- **G**：投掷手雷\n- **V**：近战攻击\n- **B**：切换射击模式\n- **T**：检视武器\n\n## 游戏模式介绍\n\n### 战术模式\n标准的团队竞技模式，两队对抗完成目标。这是新手最适合的练习模式。\n\n### 夺旗模式\n双方争夺地图中的旗帜并运回己方基地。需要良好的团队配合。\n\n### 爆破模式\n攻击方需要安放炸弹，防守方需要阻止。这是最考验战术的模式。\n\n## 新手建议\n\n### 1. 选择适合的武器\n作为新手，推荐从 **M4A1** 或 **AKM** 开始。这两把武器各方面均衡，容易上手。\n\n### 2. 多利用掩体\n三角洲行动不是跑酷游戏，保持掩护是生存的关键。移动时尽量贴着掩体，不要长时间暴露在开阔地带。\n\n### 3. 学会听声辨位\n游戏中的脚步声、枪声都能提供重要信息。佩戴耳机能大大提升你的游戏体验。\n\n### 4. 与队友配合\n这是一个团队游戏，单打独斗很难取胜。多使用语音沟通，配合队友行动。\n\n### 5. 完成新手任务\n游戏内的新手任务会奖励大量经验和解锁点，优先完成它们可以快速提升等级。\n\n## 常见问题\n\n**Q: 为什么我老是打不死人？**\nA: 检查你的网络延迟，确保射击时已经停止移动，并尝试瞄准敌人上半身。\n\n**Q: 什么武器最适合新手？**\nA: M4A1 突击步枪是最推荐的新手武器，后坐力小，伤害适中。\n\n**Q: 如何快速提升等级？**\nA: 完成每日任务和新手任务，多参与游戏，表现越好经验越多。\n\n祝你在三角洲行动的战场上取得好成绩！"
}
